{
  "type": "GepPromptArtifact",
  "at": "2026-06-03T07:31:05.630Z",
  "cycle_id": "Cycle #0146",
  "run_id": "run_1780471864694",
  "prompt_path": "/home/wszmd520520/.openclaw/workspace/skills/evolver/memory/evolution/gep_prompt_Cycle_#0146_run_1780471864694.txt",
  "meta": {
    "agent": "main",
    "drift_enabled": false,
    "review_mode": false,
    "dry_run": false,
    "mutation_id": "mut_1780471860958",
    "personality_key": "rigor=0.7|creativity=1.0|verbosity=0.3|risk_tolerance=0.4|obedience=0.9"
  }
}
